rh_python_text_parser/__init__.py
rh_python_text_parser-0.0.0.dist-info/METADATA
rh_python_text_parser-0.0.0.dist-info/WHEEL
rh_python_text_parser-0.0.0.dist-info/licenses/LICENSE
rh_python_text_parser-0.0.0.dist-info/RECORD
