Metadata-Version: 2.1
Name: rh-python-text-parser
Version: 0.0.0
Summary: Reserving the package name
Author: RHIS
License-File: LICENSE
Classifier: License :: OSI Approved :: MIT License
Classifier: Operating System :: OS Independent
Classifier: Programming Language :: Python :: 3
Requires-Python: >=3.7
